ddfacet_kernels/__init__.py
ddfacet_kernels-0.1.3.dist-info/METADATA
ddfacet_kernels-0.1.3.dist-info/WHEEL
ddfacet_kernels-0.1.3.dist-info/licenses/LICENSE
ddfacet_kernels-0.1.3.dist-info/RECORD
