Metadata-Version: 2.4
Name: ddfacet-kernels
Version: 0.1.3
Summary: Package generating DDFacet W Kernels
Author-email: Simon Perkins <simon.perkins@gmail.com>
License-File: LICENSE
Requires-Python: >=3.8
Requires-Dist: numpy>=1.24.4
Provides-Extra: dev
Requires-Dist: pre-commit>=3.5.0; extra == 'dev'
Requires-Dist: ruff>=0.11.13; extra == 'dev'
Requires-Dist: tbump>=6.11.0; extra == 'dev'
Provides-Extra: numba
Requires-Dist: numba>=0.58.1; extra == 'numba'
Provides-Extra: tests
Requires-Dist: pytest>=8.3.5; extra == 'tests'
